MANIFEST.in
setup.py
audioanalytics/__init__.py
audioanalytics/features.py
audioanalytics/model_85.h5
audioanalytics/model_85.json
audioanalytics/model_final.py
audioanalytics/predict.py
audioanalytics.egg-info/PKG-INFO
audioanalytics.egg-info/SOURCES.txt
audioanalytics.egg-info/dependency_links.txt
audioanalytics.egg-info/not-zip-safe
audioanalytics.egg-info/requires.txt
audioanalytics.egg-info/top_level.txt