Metadata-Version: 1.0
Name: audioanalytics
Version: 0.1.3
Summary: A python package to simplify the process of performing basic exploratory audio analysis and emotion detection
Home-page: https://github.com/Paymanshus/audioanalytics
Author: Pranav Kotak,Paymanshu Sharma,Shubh Lilani
Author-email: UNKNOWN
License: MIT
Platform: UNKNOWN
